{
  "imports": {
    "@deck.gl/core": "./@deck.gl/core.js",
    "@deck.gl/layers": "./@deck.gl/layers.js",
    "@hms-dbmi/viv": "./@hms-dbmi/viv.js",
    "@material-ui/core": "./@material-ui/core.js",
    "@material-ui/core/Accordion": "./@material-ui/core/Accordion.js",
    "@material-ui/core/colors/grey": "./@material-ui/core/colors/grey.js",
    "@material-ui/core/styles": "./@material-ui/core/styles.js",
    "@material-ui/icons": "./@material-ui/icons.js",
    "@material-ui/styles": "./@material-ui/styles.js",
    "@math.gl/core/dist/esm": "./@math.gl/core/dist/esm.js",
    "deck.gl": "./deck.gl.js",
    "imjoy-rpc": "./imjoy-rpc.js",
    "p-map": "./p-map.js",
    "react": "./react.js",
    "react-dom": "./react-dom.js",
    "recoil": "./recoil.js",
    "reference-spec-reader": "./reference-spec-reader.js",
    "zarr": "./zarr.js"
  }
}